{
  "project_info": {
    "project_number": "1020921082927",
    "project_id": "testprojectone-c53a8",
    "storage_bucket": "testprojectone-c53a8.appspot.com"
  },
  "client": [
    {
      "client_info": {
        "mobilesdk_app_id": "1:1020921082927:android:4be18f8e15eb8edb0f42da",
        "android_client_info": {
          "package_name": "com.test.chatappcopy"
        }
      },
      "oauth_client": [],
      "api_key": [
        {
          "current_key": "AIzaSyByTNLmOJlieEakiqamLY819NCfWUIoxLw"
        }
      ],
      "services": {
        "appinvite_service": {
          "other_platform_oauth_client": []
        }
      }
    }
  ],
  "configuration_version": "1"
}